arlas/cli/arlas_cloud.py
arlas/cli/cli.py
arlas/cli/collections.py
arlas/cli/configurations.py
arlas/cli/iam.py
arlas/cli/index.py
arlas/cli/model_infering.py
arlas/cli/org.py
arlas/cli/persist.py
arlas/cli/readers.py
arlas/cli/service.py
arlas/cli/settings.py
arlas/cli/user.py
arlas/cli/utils.py
arlas/cli/variables.py
arlas_cli-26.6.4.dist-info/METADATA
arlas_cli-26.6.4.dist-info/WHEEL
arlas_cli-26.6.4.dist-info/entry_points.txt
arlas_cli-26.6.4.dist-info/top_level.txt
arlas_cli-26.6.4.dist-info/RECORD
