Metadata-Version: 2.1
Name: arlas-cli
Version: 26.6.4
Summary: ARLAS Command line for ARLAS Management
Home-page: UNKNOWN
Author: Gisaïa
License: UNKNOWN
Platform: UNKNOWN
Requires-Python: >=3.10
Requires-Dist: click (==8.3.0)
Requires-Dist: typer (==0.19.2)
Requires-Dist: python-dateutil (==2.9.0)
Requires-Dist: envyaml (==1.10.211231)
Requires-Dist: PyJWT (==2.10.1)
Requires-Dist: attrs (==25.3.0)
Requires-Dist: python-dotenv (==1.1.1)
Requires-Dist: requests (==2.32.5)
Requires-Dist: prettytable (==3.16.0)
Requires-Dist: pydantic (==2.11.9)
Requires-Dist: alive-progress (==3.3.0)
Requires-Dist: shapely (==2.1.2)
Requires-Dist: geojson (==3.2.0)
Requires-Dist: numpy (==2.2.6)
Requires-Dist: pytest (==8.4.2)
